storyblok/__init__.py
storyblok/client.py
storyblok-0.1.1.dist-info/DESCRIPTION.rst
storyblok-0.1.1.dist-info/METADATA
storyblok-0.1.1.dist-info/RECORD
storyblok-0.1.1.dist-info/WHEEL
storyblok-0.1.1.dist-info/metadata.json
storyblok-0.1.1.dist-info/top_level.txt
